protopyenum/__init__.py
protopyenum-0.1.dist-info/METADATA
protopyenum-0.1.dist-info/RECORD
protopyenum-0.1.dist-info/WHEEL
protopyenum-0.1.dist-info/top_level.txt
