Metadata-Version: 2.1
Name: protopyenum
Version: 0.1
Summary: Protocol Buffer Enumerations in Python
Home-page: http://github.com/wtanaka/protopyenum
Author: https://wtanaka.com/
Author-email: UNKNOWN
License: Apache Software License (http://www.apache.org/licenses/LICENSE-2.0)
Platform: UNKNOWN
